.project
.pydevproject
CHANGES.txt
Contributors.txt
MANIFEST.in
README.txt
paster.ini
setup.cfg
setup.py
.settings/org.eclipse.core.resources.prefs
docs/conf.py
docs/index.rst
tests/__init__.py
tests/test_widget.py
tw/__init__.py
tw.gravatar.egg-info/PKG-INFO
tw.gravatar.egg-info/SOURCES.txt
tw.gravatar.egg-info/dependency_links.txt
tw.gravatar.egg-info/entry_points.txt
tw.gravatar.egg-info/namespace_packages.txt
tw.gravatar.egg-info/not-zip-safe
tw.gravatar.egg-info/paster_plugins.txt
tw.gravatar.egg-info/requires.txt
tw.gravatar.egg-info/top_level.txt
tw/gravatar/__init__.py
tw/gravatar/cache.py
tw/gravatar/gravatar.py
tw/gravatar/release.py
tw/gravatar/samples.py
tw/gravatar/widgets.py