Metadata-Version: 1.0
Name: tw.gravatar
Version: 0.1a0dev-20100727
Summary: inserts gravatar images
Home-page: http://code.google.com/p/twgravatar/
Author: Nicolas Laurance
Author-email: nicolas[dot]laurance<at>gmail.com
License: UNKNOWN
Keywords: toscawidgets.widgets,gravatar
Platform: UNKNOWN
Classifier: Development Status :: 3 - Alpha
Classifier: Environment :: Web Environment
Classifier: Environment :: Web Environment :: ToscaWidgets
Classifier: Topic :: Software Development :: Libraries :: Python Modules
Classifier: Topic :: Software Development :: Widget Sets
Classifier: Intended Audience :: Developers
Classifier: Operating System :: OS Independent
Classifier: Programming Language :: Python
Classifier: Framework :: TurboGears :: Widgets
Classifier: License :: OSI Approved :: GNU Affero General Public License v3
Classifier: License :: OSI Approved :: MIT License
